badcrossbar/__init__.py
badcrossbar/check.py
badcrossbar/compute.py
badcrossbar/plot.py
badcrossbar/utils.py
badcrossbar/computing/__init__.py
badcrossbar/computing/extract.py
badcrossbar/computing/fill.py
badcrossbar/computing/kcl.py
badcrossbar/computing/solve.py
badcrossbar/plotting/__init__.py
badcrossbar/plotting/color_bar.py
badcrossbar/plotting/crossbar.py
badcrossbar/plotting/devices.py
badcrossbar/plotting/shapes.py
badcrossbar/plotting/utils.py
tests/__init__.py
tests/test_check.py
tests/test_compute.py
tests/test_fill.py
tests/test_kcl.py
badcrossbar-1.1.0.dist-info/LICENSE.txt
badcrossbar-1.1.0.dist-info/METADATA
badcrossbar-1.1.0.dist-info/WHEEL
badcrossbar-1.1.0.dist-info/top_level.txt
badcrossbar-1.1.0.dist-info/RECORD
