Metadata-Version: 2.1
Name: badcrossbar
Version: 1.1.0
Summary: A Python tool for computing and plotting currents and voltages in passive crossbar arrays.
Home-page: https://github.com/joksas/badcrossbar
Author: Dovydas Joksas
Author-email: dovydas.joksas.15@ucl.ac.uk
License: UNKNOWN
Project-URL: Bug Tracker, https://github.com/joksas/badcrossbar/issues
Project-URL: Documentation, https://badcrossbar.readthedocs.io
Platform: UNKNOWN
Classifier: Programming Language :: Python :: 3
Classifier: License :: OSI Approved :: MIT License
Classifier: Operating System :: OS Independent
Requires-Python: >=3.9
License-File: LICENSE.txt
Requires-Dist: numpy (>=1.21)
Requires-Dist: pytest (>=5.4.3)
Requires-Dist: scipy (>=1.4.1)
Requires-Dist: pathvalidate (>=2.3.0)
Requires-Dist: sigfig (>=1.1.8)
Requires-Dist: pycairo (>=1.19.1)
